[
  {
    "twitterLink": "https://twitter.com/appuhafeez/status/1458985127174762499",
    "photoLink": "https://pbs.twimg.com/media/FD9bOvxUUAEOuUI?format=jpg&name=large",
    "craftsUsed": [
      "Faber-castle polychromos",
      "Primsa colorless stub",
      "Derwent artist sharpner",
      "Graphite caroal pencils"
    ]
  },
  {
    "twitterLink": "https://twitter.com/appuhafeez/status/1433056964603301890",
    "photoLink": "https://pbs.twimg.com/media/E-M9s81VQAI255r?format=jpg&name=large",
    "craftsUsed": [
      "Faber-castle polychromos",
      "Primsa colorless stub",
      "Derwent artist sharpner",
      "Graphite caroal pencils"
    ]
  },
  {
    "twitterLink": "https://twitter.com/appuhafeez/status/1417915433324142592",
    "photoLink": "https://pbs.twimg.com/media/E61ykhaVIAEnaT1?format=jpg&name=large",
    "craftsUsed": [
      "Faber-castle polychromos",
      "Primsa colorless stub",
      "Derwent artist sharpner",
      "Graphite caroal pencils"
    ]
  },
  {
    "twitterLink": "https://twitter.com/appuhafeez/status/1359174733971877888",
    "photoLink": "https://pbs.twimg.com/media/EtzCNo6VcAI62_Y?format=jpg&name=large",
    "craftsUsed": [
      "Faber-castle polychromos",
      "Primsa colorless stub",
      "Derwent artist sharpner",
      "Graphite caroal pencils"
    ]
  },

  {
    "twitterLink": "https://twitter.com/appuhafeez/status/1396145275421396998",
    "photoLink": "https://pbs.twimg.com/media/E2AauPVUcAA0Zc7?format=jpg&name=large",
    "craftsUsed": [
      "Faber-castle polychromos",
      "Primsa colorless stub",
      "Derwent artist sharpner",
      "Graphite caroal pencils"
    ]
  },
  {
    "twitterLink": "https://twitter.com/appuhafeez/status/1436358367518199808",
    "photoLink": "https://pbs.twimg.com/media/E-74UYcVcAYKjLD?format=jpg&name=large",
    "craftsUsed": [
      "Faber-castle polychromos",
      "Primsa colorless stub",
      "Derwent artist sharpner",
      "Graphite caroal pencils"
    ]
  },
  {
    "twitterLink": "https://twitter.com/appuhafeez/status/1454496352621121538",
    "photoLink": "https://pbs.twimg.com/media/FC9ouVJUcAIK9ev?format=jpg&name=large",
    "craftsUsed": [
      "Faber-castle polychromos",
      "Primsa colorless stub",
      "Derwent artist sharpner",
      "Graphite caroal pencils"
    ]
  },
  {
    "twitterLink": "https://twitter.com/appuhafeez/status/1494650934139371527",
    "photoLink": "https://pbs.twimg.com/media/FL4RGR2VQAQTjkx?format=jpg&name=large",
    "craftsUsed": [
      "Faber-castle polychromos",
      "Primsa colorless stub",
      "Derwent artist sharpner",
      "Graphite caroal pencils"
    ]
  },

  {
    "twitterLink": "https://twitter.com/appuhafeez/status/1393558924545069059",
    "photoLink": "https://pbs.twimg.com/media/E1bqc98VoAE5XrQ?format=jpg&name=large",
    "craftsUsed": [
      "Faber-castle polychromos",
      "Primsa colorless stub",
      "Derwent artist sharpner",
      "Graphite caroal pencils"
    ]
  },
  {
    "twitterLink": "https://twitter.com/appuhafeez/status/1400085078089236482",
    "photoLink": "https://pbs.twimg.com/media/E24Z894VgAcNXtZ?format=jpg&name=large",
    "craftsUsed": [
      "Faber-castle polychromos",
      "Primsa colorless stub",
      "Derwent artist sharpner",
      "Graphite caroal pencils"
    ]
  },
  {
    "twitterLink": "https://twitter.com/appuhafeez/status/1339037485733580800",
    "photoLink": "https://pbs.twimg.com/media/EpU3fmHVgAATg3L?format=jpg&name=large",
    "craftsUsed": [
      "Faber-castle polychromos",
      "Primsa colorless stub",
      "Derwent artist sharpner",
      "Graphite caroal pencils"
    ]
  }
]
